pywin10/__init__.py
pywin10-0.0.3.dist-info/LICENSE
pywin10-0.0.3.dist-info/METADATA
pywin10-0.0.3.dist-info/WHEEL
pywin10-0.0.3.dist-info/top_level.txt
pywin10-0.0.3.dist-info/RECORD
