Metadata-Version: 2.1
Name: pywin10
Version: 0.0.3
Summary: 基于Pywin32,封装了系统托盘,右键菜单,win10通知栏等功能
Home-page: https://github.com/Gaoyongxian666/pywin10
Author: Gaoyongxian666
Author-email: g1695698547@163.com
License: UNKNOWN
Project-URL: Bug Reports, https://github.com/Gaoyongxian666/pywin10
Project-URL: Source, https://github.com/Gaoyongxian666/pywin10
Platform: UNKNOWN
Classifier: Programming Language :: Python :: 3
Classifier: License :: OSI Approved :: MIT License
Classifier: Operating System :: OS Independent
Requires-Dist: pywin32
